scrapy_loader_upkeep/__init__.py
scrapy_loader_upkeep/__version__.py
scrapy_loader_upkeep/loader.py
scrapy_loader_upkeep-0.1.1.dist-info/LICENSE
scrapy_loader_upkeep-0.1.1.dist-info/METADATA
scrapy_loader_upkeep-0.1.1.dist-info/WHEEL
scrapy_loader_upkeep-0.1.1.dist-info/top_level.txt
scrapy_loader_upkeep-0.1.1.dist-info/RECORD
