Metadata-Version: 2.1
Name: scrapy-loader-upkeep
Version: 0.1.1
Summary: An alternative to the built-in ItemLoader of Scrapy which focuses on maintainability of fallback parsers.
Home-page: https://github.com/BurnzZ/scrapy-loader-upkeep
Author: Kevin Lloyd Bernal
Author-email: kevinoxy@gmail.com
License: BSD
Platform: UNKNOWN
Classifier: Environment :: Console
Classifier: Natural Language :: English
Classifier: Topic :: Scientific/Engineering :: Information Analysis
Classifier: Programming Language :: Python :: 3.8
Classifier: Topic :: Software Development :: Libraries :: Application Frameworks
Classifier: Topic :: System :: Monitoring
Classifier: Development Status :: 5 - Production/Stable
Classifier: Programming Language :: Python :: 3.7
Classifier: Programming Language :: Python
Classifier: Operating System :: OS Independent
Classifier: Topic :: Software Development
Classifier: Topic :: Software Development :: Libraries :: Python Modules
Classifier: Programming Language :: Python :: 3.6
Classifier: License :: OSI Approved :: BSD License
Classifier: Intended Audience :: Developers
Classifier: Programming Language :: Python :: Implementation :: CPython
Requires-Python: >=3.6
Requires-Dist: scrapy
